{
  "$schema": "https://ui.shadcn.com/schema/registry-item.json",
  "name": "rhf-advanced-03",
  "title": "Validated Table Filters",
  "description": "Filter an orders table through a validated search, status and amount form.",
  "dependencies": [
    "react-hook-form",
    "@hookform/resolvers",
    "zod",
    "sonner",
    "lucide-react"
  ],
  "registryDependencies": [
    "card",
    "badge",
    "empty",
    "field",
    "input",
    "select",
    "table",
    "button"
  ],
  "files": [
    {
      "path": "registry/forms/react-hook-form/advanced/rhf-advanced-03.tsx",
      "content": "'use client'\n\nimport { useState } from 'react'\nimport { Controller, useForm } from 'react-hook-form'\nimport { zodResolver } from '@hookform/resolvers/zod'\nimport { SearchIcon, SearchXIcon } from 'lucide-react'\nimport * as z from 'zod'\n\nimport { Badge } from '@/components/ui/badge'\nimport { Button } from '@/components/ui/button'\nimport {\n  Card,\n  CardContent,\n  CardDescription,\n  CardHeader,\n  CardTitle,\n} from '@/components/ui/card'\nimport {\n  Empty,\n  EmptyDescription,\n  EmptyHeader,\n  EmptyMedia,\n  EmptyTitle,\n} from '@/components/ui/empty'\nimport { Field, FieldError, FieldLabel } from '@/components/ui/field'\nimport { Input } from '@/components/ui/input'\nimport {\n  Select,\n  SelectContent,\n  SelectGroup,\n  SelectItem,\n  SelectLabel,\n  SelectTrigger,\n  SelectValue,\n} from '@/components/ui/select'\nimport {\n  Table,\n  TableBody,\n  TableCell,\n  TableHead,\n  TableHeader,\n  TableRow,\n} from '@/components/ui/table'\n\ntype OrderStatus = 'paid' | 'pending' | 'refunded'\n\ntype Order = {\n  id: string\n  customer: string\n  status: OrderStatus\n  amount: number\n}\n\nconst ORDERS: Order[] = [\n  { id: 'INV-1001', customer: 'Acme Inc.', status: 'paid', amount: 1200 },\n  { id: 'INV-1002', customer: 'Globex', status: 'pending', amount: 340 },\n  { id: 'INV-1003', customer: 'Initech', status: 'refunded', amount: 90 },\n  { id: 'INV-1004', customer: 'Umbrella Co.', status: 'paid', amount: 5400 },\n  { id: 'INV-1005', customer: 'Hooli', status: 'pending', amount: 760 },\n]\n\nconst statusVariant: Record<OrderStatus, 'default' | 'outline' | 'destructive'> =\n  {\n    paid: 'default',\n    pending: 'outline',\n    refunded: 'destructive',\n  }\n\nconst filterSchema = z.object({\n  query: z.string(),\n  status: z.enum(['all', 'paid', 'pending', 'refunded']),\n  minAmount: z\n    .string()\n    .refine(\n      (v) => v === '' || (!Number.isNaN(Number(v)) && Number(v) >= 0),\n      'Enter a non-negative number.',\n    ),\n})\n\ntype FilterValues = z.infer<typeof filterSchema>\n\nfunction applyFilters({ query, status, minAmount }: FilterValues): Order[] {\n  const q = query.trim().toLowerCase()\n  const min = minAmount === '' ? 0 : Number(minAmount)\n  return ORDERS.filter((order) => {\n    const matchesQuery =\n      q === '' ||\n      order.id.toLowerCase().includes(q) ||\n      order.customer.toLowerCase().includes(q)\n    const matchesStatus = status === 'all' || order.status === status\n    return matchesQuery && matchesStatus && order.amount >= min\n  })\n}\n\nexport function RhfAdvanced03() {\n  const form = useForm<FilterValues>({\n    resolver: zodResolver(filterSchema),\n    defaultValues: { query: '', status: 'all', minAmount: '' },\n  })\n\n  const { errors } = form.formState\n  const [results, setResults] = useState<Order[]>(ORDERS)\n\n  function onSubmit(data: FilterValues) {\n    setResults(applyFilters(data))\n  }\n\n  return (\n    <Card className=\"w-full max-w-2xl\">\n      <CardHeader>\n        <CardTitle>Orders</CardTitle>\n        <CardDescription>\n          Filter the table below — the minimum amount is validated on search.\n        </CardDescription>\n      </CardHeader>\n      <CardContent className=\"flex flex-col gap-4\">\n        <form\n          onSubmit={form.handleSubmit(onSubmit)}\n          className=\"flex flex-col gap-3 sm:flex-row sm:items-start\"\n        >\n          <Field className=\"sm:flex-1\">\n            <FieldLabel htmlFor=\"rhf-advanced-03-query\">Search</FieldLabel>\n            <Input\n              id=\"rhf-advanced-03-query\"\n              placeholder=\"Invoice or customer\"\n              {...form.register('query')}\n            />\n          </Field>\n          <Controller\n            control={form.control}\n            name=\"status\"\n            render={({ field }) => (\n              <Field className=\"sm:w-36\">\n                <FieldLabel htmlFor=\"rhf-advanced-03-status\">Status</FieldLabel>\n                <Select value={field.value} onValueChange={field.onChange}>\n                  <SelectTrigger id=\"rhf-advanced-03-status\" className=\"w-full\">\n                    <SelectValue />\n                  </SelectTrigger>\n                  <SelectContent>\n                    <SelectGroup>\n                      <SelectLabel>Status</SelectLabel>\n                      <SelectItem value=\"all\">All</SelectItem>\n                      <SelectItem value=\"paid\">Paid</SelectItem>\n                      <SelectItem value=\"pending\">Pending</SelectItem>\n                      <SelectItem value=\"refunded\">Refunded</SelectItem>\n                    </SelectGroup>\n                  </SelectContent>\n                </Select>\n              </Field>\n            )}\n          />\n          <Field className=\"sm:w-28\" data-invalid={!!errors.minAmount}>\n            <FieldLabel htmlFor=\"rhf-advanced-03-min\">Min $</FieldLabel>\n            <Input\n              id=\"rhf-advanced-03-min\"\n              inputMode=\"decimal\"\n              placeholder=\"0\"\n              aria-invalid={!!errors.minAmount}\n              {...form.register('minAmount')}\n            />\n            {errors.minAmount && <FieldError errors={[errors.minAmount]} />}\n          </Field>\n          <Button type=\"submit\" size=\"sm\" className=\"sm:mt-6\">\n            <SearchIcon className=\"size-4\" />\n            Search\n          </Button>\n        </form>\n\n        {results.length === 0 ? (\n          <Empty className=\"border\">\n            <EmptyHeader>\n              <EmptyMedia variant=\"icon\">\n                <SearchXIcon />\n              </EmptyMedia>\n              <EmptyTitle>No matching orders</EmptyTitle>\n              <EmptyDescription>\n                Try lowering the minimum or clearing the search.\n              </EmptyDescription>\n            </EmptyHeader>\n          </Empty>\n        ) : (\n          <div className=\"rounded-lg border\">\n            <Table>\n              <TableHeader>\n                <TableRow>\n                  <TableHead>Invoice</TableHead>\n                  <TableHead>Customer</TableHead>\n                  <TableHead>Status</TableHead>\n                  <TableHead className=\"text-right\">Amount</TableHead>\n                </TableRow>\n              </TableHeader>\n              <TableBody>\n                {results.map((order) => (\n                  <TableRow key={order.id}>\n                    <TableCell className=\"font-medium\">{order.id}</TableCell>\n                    <TableCell>{order.customer}</TableCell>\n                    <TableCell>\n                      <Badge\n                        variant={statusVariant[order.status]}\n                        className=\"capitalize\"\n                      >\n                        {order.status}\n                      </Badge>\n                    </TableCell>\n                    <TableCell className=\"text-right tabular-nums\">\n                      ${order.amount.toLocaleString()}\n                    </TableCell>\n                  </TableRow>\n                ))}\n              </TableBody>\n            </Table>\n          </div>\n        )}\n        <p className=\"text-muted-foreground text-sm\">\n          {results.length} of {ORDERS.length} orders\n        </p>\n      </CardContent>\n    </Card>\n  )\n}\n",
      "type": "registry:component",
      "target": "components/flx/forms/react-hook-form/rhf-advanced-03.tsx"
    }
  ],
  "type": "registry:block"
}